{
  "schemaVersion": 1,
  "id": "${mod_id}",
  "version": "${version}",
  "name": "${mod_name}",
  "description": "Add more chests to the game with bigger inventory sizes, so you can store even more items.",
  "authors": ["Nibaru"],
  "contact": {
    "homepage": "https://modrinth.com/mod/more-chests",
    "sources": "https://github.com/Nibaru/More-Chests",
    "issues": "https://github.com/Nibaru/More-Chests/issues"
  },
  "license": "LGPL-3.0",
  "icon": "assets/more_chests/icon.png",
  "environment": "*",
  "entrypoints": {
    "client": [
      "games.twinhead.morechests.client.MoreChestsClient"
    ],
    "main": [
      "games.twinhead.morechests.MoreChests"
    ],
    "fabric-datagen": [
      "games.twinhead.morechests.datagen.ModDatagen"
    ]
  },
  "depends": {
    "fabricloader": ">=${loader_version}",
    "fabric": "*",
    "minecraft": "${minecraft_version}"
  }
}